pymonads/__init__.py
pymonads/applicative.py
pymonads/either.py
pymonads/functor.py
pymonads/maybe.py
pymonads/monad.py
pymonads/py.typed
pymonads/test_either.py
pymonads/utils.py
pymonads/tests/__init__.py
pymonads/tests/applicative_laws.py
pymonads/tests/functor_laws.py
pymonads/tests/test_either.py
pymonads-0.1.5.dist-info/LICENSE
pymonads-0.1.5.dist-info/METADATA
pymonads-0.1.5.dist-info/WHEEL
pymonads-0.1.5.dist-info/top_level.txt
pymonads-0.1.5.dist-info/RECORD
