Metadata-Version: 2.1
Name: pymonads
Version: 0.1.5
Summary: Well typed functional programming abstactions in Python
Home-page: http://github.com/amackillop/pymonads
Author: Austin Mackillop
Author-email: austin.mackillop@gmail.com
License: MIT
Platform: UNKNOWN
